[
  {
    "keyword": "Feature",
    "name": "Calendar",
    "line": 1,
    "id": "calendar",
    "tags": [],
    "uri": "features/tests/salesforce/calendar.feature",
    "elements": [
      {
        "id": "calendar;verify-that-a-new-event-is-added-successfully",
        "keyword": "Scenario",
        "line": 4,
        "name": "Verify that a new event is added successfully",
        "tags": [],
        "type": "scenario",
        "steps": [
          {
            "arguments": [],
            "keyword": "Given ",
            "line": 5,
            "name": "I open the page \"salesforce\"",
            "match": {
              "location": "features/steps/sharedSteps.js:8"
            },
            "result": {
              "status": "passed",
              "duration": 5916000000000000
            }
          },
          {
            "arguments": [],
            "keyword": "And ",
            "line": 6,
            "name": "I read data from \"salesforce\"",
            "match": {
              "location": "features/steps/sharedSteps.js:29"
            },
            "result": {
              "status": "passed",
              "duration": 4000000000000
            }
          },
          {
            "arguments": [],
            "keyword": "And ",
            "line": 7,
            "name": "I populate the field \"UserName\" with \"franciscodotitexeira-gwml@force.com\"",
            "match": {
              "location": "features/steps/sharedSteps.js:39"
            },
            "result": {
              "status": "passed",
              "duration": 4092000000000000
            }
          },
          {
            "arguments": [],
            "keyword": "And ",
            "line": 8,
            "name": "I populate the field \"Password\" with \"Yosoyyo123!\"",
            "match": {
              "location": "features/steps/sharedSteps.js:39"
            },
            "result": {
              "status": "passed",
              "duration": 4039000000000000
            }
          },
          {
            "arguments": [],
            "keyword": "And ",
            "line": 9,
            "name": "I click on \"BtnLogin\"",
            "match": {
              "location": "features/steps/sharedSteps.js:33"
            },
            "result": {
              "status": "passed",
              "duration": 3409000000000000
            }
          },
          {
            "arguments": [],
            "keyword": "And ",
            "line": 10,
            "name": "I click on \"Manage\"",
            "match": {
              "location": "features/steps/sharedSteps.js:33"
            },
            "result": {
              "status": "passed",
              "duration": 9052000000000000
            }
          },
          {
            "arguments": [],
            "keyword": "And ",
            "line": 11,
            "name": "I click on \"View Calendar\"",
            "match": {
              "location": "features/steps/sharedSteps.js:33"
            },
            "result": {
              "status": "passed",
              "duration": 254000000000000
            }
          },
          {
            "arguments": [],
            "keyword": "And ",
            "line": 12,
            "name": "I click on \"New Event\"",
            "match": {
              "location": "features/steps/sharedSteps.js:33"
            },
            "result": {
              "status": "passed",
              "duration": 3945000000000000
            }
          },
          {
            "arguments": [
              {
                "rows": [
                  {
                    "cells": [
                      "Subject",
                      "testSubject"
                    ]
                  },
                  {
                    "cells": [
                      "Location",
                      "Argentina"
                    ]
                  },
                  {
                    "cells": [
                      "Description",
                      "this is an event added by an Automation test"
                    ]
                  }
                ]
              }
            ],
            "keyword": "And ",
            "line": 13,
            "name": "I populate the following fields",
            "match": {
              "location": "features/steps/sharedSteps.js:47"
            },
            "result": {
              "status": "passed",
              "duration": 22314000000000000
            }
          },
          {
            "arguments": [],
            "keyword": "And ",
            "line": 17,
            "name": "I click on \"SaveNewEvent\"",
            "match": {
              "location": "features/steps/sharedSteps.js:33"
            },
            "result": {
              "status": "passed",
              "duration": 255000000000000
            }
          },
          {
            "arguments": [],
            "keyword": "And ",
            "line": 18,
            "name": "Verifico que el campo \"ToastNewEventSaved\" contenga el texto \"was created.\"",
            "match": {
              "location": "features/steps/sharedSteps.js:85"
            },
            "result": {
              "status": "passed",
              "duration": 5104000000000000
            }
          },
          {
            "keyword": "After",
            "hidden": true,
            "match": {
              "location": "features/support/hooks.js:35"
            },
            "result": {
              "status": "passed",
              "duration": 1000000000000
            }
          },
          {
            "keyword": "After",
            "hidden": true,
            "match": {
              "location": "features/support/hooks.js:20"
            },
            "result": {
              "status": "passed",
              "duration": 2000000000000
            }
          }
        ]
      }
    ]
  }
]